{
  "bookmarks": {
    "FigS4_39": {
      "isExclusive": true,
      "sourceDisplays": [
        {
          "imageDisplay": {
            "color": "(r=255,g=255,b=255,a=255)",
            "contrastLimits": [
              0.0,
              255.0
            ],
            "name": "Sample5_image",
            "opacity": 1.0,
            "showImagesIn3d": false,
            "sources": [
              "Sample5_image"
            ]
          }
        }
      ],
      "uiSelectionGroup": "bookmark",
      "viewerTransform": {
        "normalizedAffine": [
          0.002162533359640553,
          4.1506194542638714e-19,
          3.774716020196222e-05,
          -5.1525761151239795,
          -4.16520827777379e-19,
          0.0021628627741171118,
          7.995712318940757e-20,
          -1.664520899727723,
          -3.774716020196222e-05,
          -8.721423610822933e-20,
          0.002162533359640553,
          -2.7516778475753956
        ]
      }
    }
  }
}