{
  "bookmarks": {
    "FigS4_6.1": {
      "isExclusive": true,
      "sourceDisplays": [
        {
          "imageDisplay": {
            "color": "(r=255,g=255,b=255,a=255)",
            "contrastLimits": [
              0.0,
              255.0
            ],
            "name": "Sample3_image",
            "opacity": 1.0,
            "showImagesIn3d": false,
            "sources": [
              "Sample3_image"
            ]
          }
        }
      ],
      "uiSelectionGroup": "bookmark",
      "viewerTransform": {
        "normalizedAffine": [
          0.00086021779297123,
          -5.782411586589346e-20,
          5.782411586589346e-20,
          -0.20287031941469244,
          5.782411586589346e-20,
          0.00086021779297123,
          -7.228014483236684e-20,
          -0.17849186332736597,
          -5.782411586589346e-20,
          7.228014483236684e-20,
          0.00086021779297123,
          -0.32860319691500983
        ]
      }
    }
  }
}